fisspy/__init__.py
fisspy/cm.py
fisspy/makevideo.py
fisspy/align/__init__.py
fisspy/align/alignment.py
fisspy/align/base.py
fisspy/analysis/__init__.py
fisspy/analysis/doppler.py
fisspy/analysis/filter.py
fisspy/analysis/forecast.py
fisspy/analysis/ofe.py
fisspy/analysis/tdmap.py
fisspy/analysis/wavelet.py
fisspy/correction/__init__.py
fisspy/correction/correction.py
fisspy/correction/get_inform.py
fisspy/data/__init__.py
fisspy/data/_sample.py
fisspy/data/download.py
fisspy/data/sample.py
fisspy/image/__init__.py
fisspy/image/interactive_image.py
fisspy/image/raster_set.py
fisspy/inversion/__init__.py
fisspy/inversion/_mlsi.py
fisspy/inversion/_mlsi_base.py
fisspy/io/__init__.py
fisspy/io/read.py
fisspy/preprocess/__init__.py
fisspy/preprocess/proc_base.py
fisspy/preprocess/proc_gui.py
fisspy/preprocess/t_y_sh.py
fisspy/read/__init__.py
fisspy/read/read_factory.py
fisspy/read/readbase.py
fisspy-1.2.1.dist-info/LICENSE.txt
fisspy-1.2.1.dist-info/METADATA
fisspy-1.2.1.dist-info/WHEEL
fisspy-1.2.1.dist-info/top_level.txt
fisspy-1.2.1.dist-info/RECORD
